TOCCI/fig3_51/fig3_51.vhdl
-- Intermediate variables
-- Digital systems Tocci 10ed.
-- Mauricio Taffarel
-- 26/07/2020

entity fig3_51 is
	port (
		a,b,c	:in bit;
		y	:out bit
	     );
end fig3_51;
architecture ckt of fig3_51 is
	signal m :bit;
begin
	m <= a and b;
	y <= m or c;

end ckt;

fig3_51/fig3_51_tb.vhdl
-- Intermediate variables [TESTS]
-- Digital systems Tocci 10ed.
-- Mauricio Taffarel
-- 26/07/2020

entity fig3_51_tb is
end fig3_51_tb;

architecture ckt of fig3_51_tb is
	component fig3_51 is
		port (
			a,b,c	:in bit;
			y	:out bit
	     	);
	end component;
	signal a,b,c,y : bit;	
begin
	instance: fig3_51 port map(a=>a, b=>b, c=>c, y=>y);

	process begin
		a <= '0';
		b <= '0';
		c <= '0';
		wait for 1 ns;
		
		a <= '0';
		b <= '0';
		c <= '1';
		wait for 1 ns;

		a <= '0';
		b <= '1';
		c <= '0';
		wait for 1 ns;

		a <= '0';
		b <= '1';
		c <= '1';
		wait for 1 ns;

		a <= '1';
		b <= '0';
		c <= '0';
		wait for 1 ns;
		
		a <= '1';
		b <= '0';
		c <= '1';
		wait for 1 ns;

		a <= '1';
		b <= '1';
		c <= '0';
		wait for 1 ns;

		a <= '1';
		b <= '1';
		c <= '1';
		wait for 1 ns;
		
		assert false report "END";
		wait;
	end process;
end ckt;

fig3_51/wave.vcd
$date
  Sun Jul 26 16:55:52 2020
$end
$version
  GHDL v0
$end
$timescale
  1 fs
$end
$scope module standard $end
$upscope $end
$scope module fig3_51_tb $end
$var reg 1 ! a $end
$var reg 1 " b $end
$var reg 1 # c $end
$var reg 1 $ y $end
$scope module instance $end
$var reg 1 % a $end
$var reg 1 & b $end
$var reg 1 ' c $end
$var reg 1 ( y $end
$var reg 1 ) m $end
$upscope $end
$upscope $end
$enddefinitions $end
#0
0!
0"
0#
0$
0%
0&
0'
0(
0)
#1000000
1#
1$
1'
1(
#2000000
1"
0#
0$
1&
0'
0(
#3000000
1#
1$
1'
1(
#4000000
1!
0"
0#
0$
1%
0&
0'
0(
#5000000
1#
1$
1'
1(
#6000000
1"
0#
1$
1&
0'
1(
1)
#7000000
1#
1'
